tabluar_mind/__init__.py
tabluar_mind/main.py
tabluar_mind-0.1.0.dist-info/METADATA
tabluar_mind-0.1.0.dist-info/WHEEL
tabluar_mind-0.1.0.dist-info/RECORD
